prefect_hightouch/__init__.py
prefect_hightouch/_version.py
prefect_hightouch/exceptions.py
prefect_hightouch/api_client/__init__.py
prefect_hightouch/api_client/client.py
prefect_hightouch/api_client/types.py
prefect_hightouch/api_client/api/__init__.py
prefect_hightouch/api_client/api/default/__init__.py
prefect_hightouch/api_client/api/default/get_destination.py
prefect_hightouch/api_client/api/default/get_model.py
prefect_hightouch/api_client/api/default/get_source.py
prefect_hightouch/api_client/api/default/get_sync.py
prefect_hightouch/api_client/api/default/list_destination.py
prefect_hightouch/api_client/api/default/list_model.py
prefect_hightouch/api_client/api/default/list_source.py
prefect_hightouch/api_client/api/default/list_sync.py
prefect_hightouch/api_client/api/default/list_sync_runs.py
prefect_hightouch/api_client/api/default/trigger_run.py
prefect_hightouch/api_client/api/default/trigger_run_custom.py
prefect_hightouch/api_client/models/__init__.py
prefect_hightouch/api_client/models/cron_schedule.py
prefect_hightouch/api_client/models/dbt_schedule.py
prefect_hightouch/api_client/models/dbt_schedule_account.py
prefect_hightouch/api_client/models/dbt_schedule_job.py
prefect_hightouch/api_client/models/destination.py
prefect_hightouch/api_client/models/destination_configuration.py
prefect_hightouch/api_client/models/interval.py
prefect_hightouch/api_client/models/interval_schedule.py
prefect_hightouch/api_client/models/interval_unit.py
prefect_hightouch/api_client/models/list_destination_order_by.py
prefect_hightouch/api_client/models/list_destination_response_200.py
prefect_hightouch/api_client/models/list_model_order_by.py
prefect_hightouch/api_client/models/list_model_response_200.py
prefect_hightouch/api_client/models/list_source_order_by.py
prefect_hightouch/api_client/models/list_source_response_200.py
prefect_hightouch/api_client/models/list_sync_order_by.py
prefect_hightouch/api_client/models/list_sync_response_200.py
prefect_hightouch-0.2.1.dist-info/LICENSE
prefect_hightouch-0.2.1.dist-info/METADATA
prefect_hightouch-0.2.1.dist-info/WHEEL
prefect_hightouch-0.2.1.dist-info/entry_points.txt
prefect_hightouch-0.2.1.dist-info/top_level.txt
prefect_hightouch-0.2.1.dist-info/RECORD
